pycvt/__init__.py
pycvt/annotations/yolo.py
pycvt/clolors/__init__.py
pycvt/clolors/colors.py
pycvt/paster/__init__.py
pycvt/paster/paste_image.py
pycvt/static/__init__.py
pycvt/utils/__init__.py
pycvt/utils/image_utils.py
pycvt/vision/__init__.py
pycvt/vision/bbox.py
pycvt/vision/plot_boxes.py
pycvt/vision/utils.py
pycvt-0.0.1.post202601010001.dist-info/METADATA
pycvt-0.0.1.post202601010001.dist-info/WHEEL
pycvt-0.0.1.post202601010001.dist-info/top_level.txt
pycvt-0.0.1.post202601010001.dist-info/RECORD
