Metadata-Version: 2.4
Name: pycvt
Version: 0.0.1.post202601010001
Summary: pycvt is a Python package designed for computer vision utilities, including YOLO annotation handling, image manipulation, bounding box plotting, and data conversion tools.
Author-email: ferretsprite <ferret-sprite-goon@duck.com>
Project-URL: Homepage, https://github.com/xx025
Project-URL: Repository, https://github.com/
Project-URL: Documentation, https://github.com/
Requires-Python: >=3.10
Requires-Dist: distinctipy>=1.3.4
Requires-Dist: easyfont>=0.0.1.post10
